setup.py
cedict/__init__.py
cedict/cedict_parser.py
cedict/pinyin.py
pycedict.egg-info/PKG-INFO
pycedict.egg-info/SOURCES.txt
pycedict.egg-info/dependency_links.txt
pycedict.egg-info/not-zip-safe
pycedict.egg-info/top_level.txt