Metadata-Version: 1.0
Name: pycedict
Version: 0.9.2
Summary: A library for parsing CEDict and adding tone marks to pinyin
Home-page: https://github.com/jdillworth/pycedict
Author: Jeremy Dillworth
Author-email: jeremy@winter14.com
License: New BSD
Platform: UNKNOWN
